wristwatch/__init__.py
wristwatch/wristwatch.py
wristwatch-1.3.0.dist-info/LICENSE
wristwatch-1.3.0.dist-info/METADATA
wristwatch-1.3.0.dist-info/WHEEL
wristwatch-1.3.0.dist-info/entry_points.txt
wristwatch-1.3.0.dist-info/top_level.txt
wristwatch-1.3.0.dist-info/RECORD
