Metadata-Version: 2.1
Name: wristwatch
Version: 1.3.0
Summary: Yet another Python watcher for website updates.
Home-page: https://github.com/zWolfrost/wristwatch
Author: zWolfrost
License: UNKNOWN
Platform: UNKNOWN
License-File: LICENSE
Requires-Dist: beautifulsoup4 >=4.11.0
Requires-Dist: browser-cookie3 >=0.19.0
Requires-Dist: chime >=0.7.0
Requires-Dist: selenium >=4.19.0
